odoo/addons/pms/README.rst
odoo/addons/pms/__init__.py
odoo/addons/pms/__manifest__.py
odoo/addons/pms/init_hook.py
odoo/addons/pms/controllers/__init__.py
odoo/addons/pms/controllers/pms_portal.py
odoo/addons/pms/data/cron_jobs.xml
odoo/addons/pms/data/menus.xml
odoo/addons/pms/data/pms_cancelled_reservation_email_template.xml
odoo/addons/pms/data/pms_confirmed_reservation_email_template.xml
odoo/addons/pms/data/pms_data.xml
odoo/addons/pms/data/pms_modified_reservation_email_template.xml
odoo/addons/pms/data/pms_precheckin_invitation_email_template.xml
odoo/addons/pms/data/pms_sequence.xml
odoo/addons/pms/data/queue_data.xml
odoo/addons/pms/data/queue_job_function_data.xml
odoo/addons/pms/data/traveller_report_paperformat.xml
odoo/addons/pms/demo/airbnb-logo.svg
odoo/addons/pms/demo/booking-logo.svg
odoo/addons/pms/demo/pms_folio.xml
odoo/addons/pms/demo/pms_master_data.xml
odoo/addons/pms/demo/pms_master_data_no_update.xml
odoo/addons/pms/demo/pms_reservation.xml
odoo/addons/pms/i18n/de.po
odoo/addons/pms/i18n/es.po
odoo/addons/pms/i18n/it.po
odoo/addons/pms/i18n/pms.pot
odoo/addons/pms/migrations/16.0.0.1.0/pre-migration.py
odoo/addons/pms/migrations/16.0.0.2.0/post-migration.py
odoo/addons/pms/migrations/16.0.0.3.0/pre-migration.py
odoo/addons/pms/migrations/16.0.1.0.0/pre-migration.py
odoo/addons/pms/models/__init__.py
odoo/addons/pms/models/account_analytic_line.py
odoo/addons/pms/models/account_bank_statement.py
odoo/addons/pms/models/account_bank_statement_line.py
odoo/addons/pms/models/account_journal.py
odoo/addons/pms/models/account_move.py
odoo/addons/pms/models/account_move_line.py
odoo/addons/pms/models/account_payment.py
odoo/addons/pms/models/folio_sale_line.py
odoo/addons/pms/models/ir_config_parameter.py
odoo/addons/pms/models/ir_http.py
odoo/addons/pms/models/ir_pms_property.py
odoo/addons/pms/models/mail_compose_message.py
odoo/addons/pms/models/payment_provider.py
odoo/addons/pms/models/payment_transaction.py
odoo_addon_pms-16.0.2.5.0.1.dist-info/METADATA
odoo_addon_pms-16.0.2.5.0.1.dist-info/WHEEL
odoo_addon_pms-16.0.2.5.0.1.dist-info/top_level.txt
odoo_addon_pms-16.0.2.5.0.1.dist-info/RECORD
