Metadata-Version: 2.1
Name: odoo-addon-pms
Version: 16.0.2.5.0.1
Summary: A property management system
Home-page: https://github.com/OCA/pms
Author: Commit [Sun], Odoo Community Association (OCA)
Author-email: support@odoo-community.org
License: AGPL-3
Classifier: Programming Language :: Python
Classifier: Framework :: Odoo
Classifier: Framework :: Odoo :: 16.0
Classifier: License :: OSI Approved :: GNU Affero General Public License v3
Classifier: Development Status :: 4 - Beta
Requires-Python: >=3.10
Requires-Dist: odoo-addon-multi-pms-properties<16.1dev,>=16.0dev
Requires-Dist: odoo-addon-partner-contact-birthdate<16.1dev,>=16.0dev
Requires-Dist: odoo-addon-partner-contact-gender<16.1dev,>=16.0dev
Requires-Dist: odoo-addon-partner-contact-nationality<16.1dev,>=16.0dev
Requires-Dist: odoo-addon-partner-firstname<16.1dev,>=16.0dev
Requires-Dist: odoo-addon-queue-job<16.1dev,>=16.0dev
Requires-Dist: odoo-addon-web-timeline<16.1dev,>=16.0dev
Requires-Dist: odoo<16.1dev,>=16.0a
Requires-Dist: openupgradelib
